{"repeat":false,"random":false,"durationBetweenWaves":"1000","waves":[{"name":"BuzzerableCprIlsCalibrationFlowOperation/Changed","id":"9b159c86-695f-44f1-960e-c114fcf3e87b","data":{"resourceName":"BuzzerableCprIlsCalibrationFlowOperation","resourceContent":{"UseDefaultParameters":false,"LastCalibrationTime":"2023-09-17T14:58:15.4794191+03:00","CalibrationOperationDummy":false,"CalibrationState":"NotStarted","CalibrationResult":{"Status":"None","ResultMessages":[]},"CommitAvailability":{"IsAvailable":false,"UnavailableReasons":[{"ID":"CalibrationNotStarted","LocalizationID":"SE.AppDefinitions.PressMessages.Calibrations.CalibrationsGeneral.CalibrationNotStarted","Data":{}}]},"CommitState":"Idle","CancelAvailability":{"IsAvailable":true,"UnavailableReasons":[]},"CancelState":"Idle","CalibrationId":"b0d980ad-92d5-479c-ae5e-c94e94c366a8","ScopeId":"af594a17-26ea-4ad5-8e74-fcbc575f6a6f","Errors":[],"StartAvailability":{"IsAvailable":false,"UnavailableReasons":[{"ID":"OperationStarting","LocalizationID":"SE.AppDefinitions.PressMessages.General.OperationStarting","Data":{}}]},"StopAvailability":{"IsAvailable":false,"UnavailableReasons":[{"ID":"OperationNotInProgress","LocalizationID":"SE.AppDefinitions.PressMessages.General.OperationNotInProgress","Data":{}}]},"State":"Idle","BuzzerableOperationState":"BuzzerLocking","BuzzerState":"NotNeeded","BuzzerType":"ForcedMethod1"},"NotificationType":"Changed"},"description":"BuzzerableCprIlsCalibrationFlowOperation/Changed"},{"name":"BuzzerableCprIlsCalibrationFlowOperation/Changed","id":"e0f0e503-246b-49f5-81c6-dcf6ed0c6721","data":{"resourceName":"BuzzerableCprIlsCalibrationFlowOperation","resourceContent":{"UseDefaultParameters":false,"LastCalibrationTime":"2023-09-17T14:58:15.4794191+03:00","CalibrationOperationDummy":false,"CalibrationState":"NotStarted","CalibrationResult":{"Status":"None","ResultMessages":[]},"CommitAvailability":{"IsAvailable":false,"UnavailableReasons":[{"ID":"CalibrationNotStarted","LocalizationID":"SE.AppDefinitions.PressMessages.Calibrations.CalibrationsGeneral.CalibrationNotStarted","Data":{}}]},"CommitState":"Idle","CancelAvailability":{"IsAvailable":true,"UnavailableReasons":[]},"CancelState":"Idle","CalibrationId":"b0d980ad-92d5-479c-ae5e-c94e94c366a8","ScopeId":"af594a17-26ea-4ad5-8e74-fcbc575f6a6f","Errors":[],"StartAvailability":{"IsAvailable":false,"UnavailableReasons":[{"ID":"OperationInProgress","LocalizationID":"SE.AppDefinitions.PressMessages.General.OperationInProgress","Data":{}}]},"StopAvailability":{"IsAvailable":false,"UnavailableReasons":[{"ID":"OperationStarting","LocalizationID":"SE.AppDefinitions.PressMessages.General.OperationStarting","Data":{}}]},"State":"InProgress","BuzzerableOperationState":"OperationInProgress","BuzzerState":"NotNeeded","BuzzerType":"ForcedMethod1"},"NotificationType":"Changed"},"description":"BuzzerableCprIlsCalibrationFlowOperation/Changed"},{"name":"BuzzerableCprIlsCalibrationFlowOperation/Changed","id":"1e823116-fd09-44eb-b996-6543b8b82a25","data":{"resourceName":"BuzzerableCprIlsCalibrationFlowOperation","resourceContent":{"UseDefaultParameters":false,"LastCalibrationTime":"2023-09-17T14:58:15.4794191+03:00","CalibrationOperationDummy":false,"CalibrationState":"OperationInProgress","CalibrationResult":{"Status":"None","ResultMessages":[]},"CommitAvailability":{"IsAvailable":false,"UnavailableReasons":[{"ID":"OperationInProgress","LocalizationID":"SE.AppDefinitions.PressMessages.General.OperationInProgress","Data":{}}]},"CommitState":"Idle","CancelAvailability":{"IsAvailable":false,"UnavailableReasons":[{"ID":"OperationInProgress","LocalizationID":"SE.AppDefinitions.PressMessages.General.OperationInProgress","Data":{}}]},"CancelState":"Idle","CalibrationId":"8ef3ab55-8738-4104-9372-f94ca0df8233","ScopeId":"af594a17-26ea-4ad5-8e74-fcbc575f6a6f","Errors":[],"StartAvailability":{"IsAvailable":false,"UnavailableReasons":[{"ID":"OperationInProgress","LocalizationID":"SE.AppDefinitions.PressMessages.General.OperationInProgress","Data":{}}]},"StopAvailability":{"IsAvailable":true,"UnavailableReasons":[]},"State":"InProgress","BuzzerableOperationState":"OperationInProgress","BuzzerState":"NotNeeded","BuzzerType":"ForcedMethod1"},"NotificationType":"Changed"},"description":"BuzzerableCprIlsCalibrationFlowOperation/Changed"},{"name":"BuzzerableCprIlsCalibrationFlowOperation/Changed","id":"fed1c8ee-ef64-48be-8346-2a307a63c911","data":{"resourceName":"BuzzerableCprIlsCalibrationFlowOperation","resourceContent":{"UseDefaultParameters":false,"LastCalibrationTime":"2023-09-17T14:58:15.4794191+03:00","CalibrationOperationDummy":false,"CalibrationState":"OperationInProgress","CalibrationResult":{"Status":"None","ResultMessages":[]},"CommitAvailability":{"IsAvailable":false,"UnavailableReasons":[{"ID":"OperationInProgress","LocalizationID":"SE.AppDefinitions.PressMessages.General.OperationInProgress","Data":{}}]},"CommitState":"Idle","CancelAvailability":{"IsAvailable":false,"UnavailableReasons":[{"ID":"OperationInProgress","LocalizationID":"SE.AppDefinitions.PressMessages.General.OperationInProgress","Data":{}}]},"CancelState":"Idle","CalibrationId":"8ef3ab55-8738-4104-9372-f94ca0df8233","ScopeId":"af594a17-26ea-4ad5-8e74-fcbc575f6a6f","Errors":[],"StartAvailability":{"IsAvailable":false,"UnavailableReasons":[{"ID":"OperationInProgress","LocalizationID":"SE.AppDefinitions.PressMessages.General.OperationInProgress","Data":{}}]},"StopAvailability":{"IsAvailable":true,"UnavailableReasons":[]},"State":"InProgress","BuzzerableOperationState":"OperationInProgress","BuzzerState":"Needed","BuzzerType":"ForcedMethod1"},"NotificationType":"Changed"},"description":"BuzzerableCprIlsCalibrationFlowOperation/Changed"},{"name":"BuzzerableCprIlsCalibrationFlowOperation/Changed","id":"a8b62432-7e41-4455-92e3-f8792b3689fe","data":{"resourceName":"BuzzerableCprIlsCalibrationFlowOperation","resourceContent":{"UseDefaultParameters":false,"LastCalibrationTime":"2023-09-17T14:58:15.4794191+03:00","CalibrationOperationDummy":false,"CalibrationState":"OperationCompletionInProgress","CalibrationResult":{"Status":"Failed","ResultMessages":[{"ID":"CalibrationInterrupted","LocalizationID":"SE.AppDefinitions.PressMessages.Internal.Calibrations.CalibrationInterrupted","Data":{}}]},"CommitAvailability":{"IsAvailable":false,"UnavailableReasons":[{"ID":"OperationInProgress","LocalizationID":"SE.AppDefinitions.PressMessages.General.OperationInProgress","Data":{}}]},"CommitState":"Idle","CancelAvailability":{"IsAvailable":false,"UnavailableReasons":[{"ID":"OperationInProgress","LocalizationID":"SE.AppDefinitions.PressMessages.General.OperationInProgress","Data":{}}]},"CancelState":"Idle","CalibrationId":"8ef3ab55-8738-4104-9372-f94ca0df8233","ScopeId":"af594a17-26ea-4ad5-8e74-fcbc575f6a6f","Errors":[],"StartAvailability":{"IsAvailable":false,"UnavailableReasons":[{"ID":"OperationInProgress","LocalizationID":"SE.AppDefinitions.PressMessages.General.OperationInProgress","Data":{}}]},"StopAvailability":{"IsAvailable":false,"UnavailableReasons":[{"ID":"OperationNotInProgress","LocalizationID":"SE.AppDefinitions.PressMessages.General.OperationNotInProgress","Data":{}}]},"State":"InProgress","BuzzerableOperationState":"OperationInProgress","BuzzerState":"Needed","BuzzerType":"ForcedMethod1"},"NotificationType":"Changed"},"description":"BuzzerableCprIlsCalibrationFlowOperation/Changed"},{"name":"BuzzerableCprIlsCalibrationFlowOperation/Changed","id":"911b64b7-194a-4fde-8a51-9100c2e83ce3","data":{"resourceName":"BuzzerableCprIlsCalibrationFlowOperation","resourceContent":{"UseDefaultParameters":false,"LastCalibrationTime":"2023-09-17T14:58:15.4794191+03:00","CalibrationOperationDummy":false,"CalibrationState":"OperationCompleted","CalibrationResult":{"Status":"Failed","ResultMessages":[{"ID":"CalibrationInterrupted","LocalizationID":"SE.AppDefinitions.PressMessages.Internal.Calibrations.CalibrationInterrupted","Data":{}}]},"CommitAvailability":{"IsAvailable":false,"UnavailableReasons":[{"ID":"CalibrationFailed","LocalizationID":"SE.AppDefinitions.PressMessages.Calibrations.CalibrationsGeneral.CalibrationFailed","Data":{}}]},"CommitState":"Idle","CancelAvailability":{"IsAvailable":false,"UnavailableReasons":[{"ID":"LPHNotReady","LocalizationID":"SE.AppDefinitions.PressMessages.LPH.LPHNotReady","Data":{"LPHID":{"Value":6,"Unit":"NoUnits"}}},{"ID":"LPHNotReady","LocalizationID":"SE.AppDefinitions.PressMessages.LPH.LPHNotReady","Data":{"LPHID":{"Value":1,"Unit":"NoUnits"}}},{"ID":"LPHNotReady","LocalizationID":"SE.AppDefinitions.PressMessages.LPH.LPHNotReady","Data":{"LPHID":{"Value":2,"Unit":"NoUnits"}}},{"ID":"LPHNotReady","LocalizationID":"SE.AppDefinitions.PressMessages.LPH.LPHNotReady","Data":{"LPHID":{"Value":3,"Unit":"NoUnits"}}},{"ID":"LPHNotReady","LocalizationID":"SE.AppDefinitions.PressMessages.LPH.LPHNotReady","Data":{"LPHID":{"Value":4,"Unit":"NoUnits"}}},{"ID":"LPHNotReady","LocalizationID":"SE.AppDefinitions.PressMessages.LPH.LPHNotReady","Data":{"LPHID":{"Value":5,"Unit":"NoUnits"}}}]},"CancelState":"Idle","CalibrationId":"8ef3ab55-8738-4104-9372-f94ca0df8233","ScopeId":"af594a17-26ea-4ad5-8e74-fcbc575f6a6f","Errors":[],"StartAvailability":{"IsAvailable":false,"UnavailableReasons":[{"ID":"ILSNotReady","LocalizationID":"SE.AppDefinitions.PressMessages.ILS.ILSNotReady","Data":{}},{"ID":"CprIlsRecalibrationNotAvailable","LocalizationID":"SE.AppDefinitions.PressMessages.Calibrations.CprIlsCalibration.CprIlsRecalibrationNotAvailable","Data":{}},{"ID":"OperationInProgress","LocalizationID":"SE.AppDefinitions.PressMessages.General.OperationInProgress","Data":{}}]},"StopAvailability":{"IsAvailable":false,"UnavailableReasons":[{"ID":"OperationNotInProgress","LocalizationID":"SE.AppDefinitions.PressMessages.General.OperationNotInProgress","Data":{}}]},"State":"Failed","BuzzerableOperationState":"OperationCompleted","BuzzerState":"Needed","BuzzerType":"ForcedMethod1"},"NotificationType":"Changed"},"description":"BuzzerableCprIlsCalibrationFlowOperation/Changed"},{"name":"BuzzerableCprIlsCalibrationFlowOperation/Changed","id":"0cf337a9-57bf-43fa-be9a-2768b7dc925d","data":{"resourceName":"BuzzerableCprIlsCalibrationFlowOperation","resourceContent":{"UseDefaultParameters":false,"LastCalibrationTime":"2023-09-17T14:58:15.4794191+03:00","CalibrationOperationDummy":false,"CalibrationState":"OperationCompleted","CalibrationResult":{"Status":"Failed","ResultMessages":[{"ID":"CalibrationInterrupted","LocalizationID":"SE.AppDefinitions.PressMessages.Internal.Calibrations.CalibrationInterrupted","Data":{}}]},"CommitAvailability":{"IsAvailable":false,"UnavailableReasons":[{"ID":"CalibrationFailed","LocalizationID":"SE.AppDefinitions.PressMessages.Calibrations.CalibrationsGeneral.CalibrationFailed","Data":{}}]},"CommitState":"Idle","CancelAvailability":{"IsAvailable":false,"UnavailableReasons":[{"ID":"LPHNotReady","LocalizationID":"SE.AppDefinitions.PressMessages.LPH.LPHNotReady","Data":{"LPHID":{"Value":6,"Unit":"NoUnits"}}},{"ID":"LPHNotReady","LocalizationID":"SE.AppDefinitions.PressMessages.LPH.LPHNotReady","Data":{"LPHID":{"Value":1,"Unit":"NoUnits"}}},{"ID":"LPHNotReady","LocalizationID":"SE.AppDefinitions.PressMessages.LPH.LPHNotReady","Data":{"LPHID":{"Value":2,"Unit":"NoUnits"}}},{"ID":"LPHNotReady","LocalizationID":"SE.AppDefinitions.PressMessages.LPH.LPHNotReady","Data":{"LPHID":{"Value":3,"Unit":"NoUnits"}}},{"ID":"LPHNotReady","LocalizationID":"SE.AppDefinitions.PressMessages.LPH.LPHNotReady","Data":{"LPHID":{"Value":4,"Unit":"NoUnits"}}},{"ID":"LPHNotReady","LocalizationID":"SE.AppDefinitions.PressMessages.LPH.LPHNotReady","Data":{"LPHID":{"Value":5,"Unit":"NoUnits"}}}]},"CancelState":"Idle","CalibrationId":"8ef3ab55-8738-4104-9372-f94ca0df8233","ScopeId":"af594a17-26ea-4ad5-8e74-fcbc575f6a6f","Errors":[],"StartAvailability":{"IsAvailable":false,"UnavailableReasons":[{"ID":"CprIlsRecalibrationNotAvailable","LocalizationID":"SE.AppDefinitions.PressMessages.Calibrations.CprIlsCalibration.CprIlsRecalibrationNotAvailable","Data":{}},{"ID":"OperationInProgress","LocalizationID":"SE.AppDefinitions.PressMessages.General.OperationInProgress","Data":{}}]},"StopAvailability":{"IsAvailable":false,"UnavailableReasons":[{"ID":"OperationNotInProgress","LocalizationID":"SE.AppDefinitions.PressMessages.General.OperationNotInProgress","Data":{}}]},"State":"Failed","BuzzerableOperationState":"OperationCompleted","BuzzerState":"Needed","BuzzerType":"ForcedMethod1"},"NotificationType":"Changed"},"description":"BuzzerableCprIlsCalibrationFlowOperation/Changed"},{"name":"BuzzerableCprIlsCalibrationFlowOperation/Changed","id":"f1e7a9ae-9728-4f1a-abec-b5d9a97d4366","data":{"resourceName":"BuzzerableCprIlsCalibrationFlowOperation","resourceContent":{"UseDefaultParameters":false,"LastCalibrationTime":"2023-09-17T14:58:15.4794191+03:00","CalibrationOperationDummy":false,"CalibrationState":"OperationCompleted","CalibrationResult":{"Status":"Failed","ResultMessages":[{"ID":"CalibrationInterrupted","LocalizationID":"SE.AppDefinitions.PressMessages.Internal.Calibrations.CalibrationInterrupted","Data":{}}]},"CommitAvailability":{"IsAvailable":false,"UnavailableReasons":[{"ID":"CalibrationFailed","LocalizationID":"SE.AppDefinitions.PressMessages.Calibrations.CalibrationsGeneral.CalibrationFailed","Data":{}}]},"CommitState":"Idle","CancelAvailability":{"IsAvailable":false,"UnavailableReasons":[{"ID":"LPHNotReady","LocalizationID":"SE.AppDefinitions.PressMessages.LPH.LPHNotReady","Data":{"LPHID":{"Value":6,"Unit":"NoUnits"}}},{"ID":"LPHNotReady","LocalizationID":"SE.AppDefinitions.PressMessages.LPH.LPHNotReady","Data":{"LPHID":{"Value":1,"Unit":"NoUnits"}}},{"ID":"LPHNotReady","LocalizationID":"SE.AppDefinitions.PressMessages.LPH.LPHNotReady","Data":{"LPHID":{"Value":2,"Unit":"NoUnits"}}},{"ID":"LPHNotReady","LocalizationID":"SE.AppDefinitions.PressMessages.LPH.LPHNotReady","Data":{"LPHID":{"Value":3,"Unit":"NoUnits"}}},{"ID":"LPHNotReady","LocalizationID":"SE.AppDefinitions.PressMessages.LPH.LPHNotReady","Data":{"LPHID":{"Value":4,"Unit":"NoUnits"}}},{"ID":"LPHNotReady","LocalizationID":"SE.AppDefinitions.PressMessages.LPH.LPHNotReady","Data":{"LPHID":{"Value":5,"Unit":"NoUnits"}}}]},"CancelState":"Idle","CalibrationId":"8ef3ab55-8738-4104-9372-f94ca0df8233","ScopeId":"af594a17-26ea-4ad5-8e74-fcbc575f6a6f","Errors":[],"StartAvailability":{"IsAvailable":false,"UnavailableReasons":[{"ID":"CprIlsRecalibrationNotAvailable","LocalizationID":"SE.AppDefinitions.PressMessages.Calibrations.CprIlsCalibration.CprIlsRecalibrationNotAvailable","Data":{}},{"ID":"PrintSessionInProgress","LocalizationID":"SE.AppDefinitions.PressMessages.PrintOperation.PrintSessionInProgress","Data":{}}]},"StopAvailability":{"IsAvailable":false,"UnavailableReasons":[{"ID":"OperationNotInProgress","LocalizationID":"SE.AppDefinitions.PressMessages.General.OperationNotInProgress","Data":{}}]},"State":"Failed","BuzzerableOperationState":"OperationCompleted","BuzzerState":"Needed","BuzzerType":"ForcedMethod1"},"NotificationType":"Changed"},"description":"BuzzerableCprIlsCalibrationFlowOperation/Changed"},{"name":"BuzzerableCprIlsCalibrationFlowOperation/Changed","id":"2f2efffb-5153-44ca-b8e8-2c2766e661d6","data":{"resourceName":"BuzzerableCprIlsCalibrationFlowOperation","resourceContent":{"UseDefaultParameters":false,"LastCalibrationTime":"2023-09-17T14:58:15.4794191+03:00","CalibrationOperationDummy":false,"CalibrationState":"OperationCompleted","CalibrationResult":{"Status":"Failed","ResultMessages":[{"ID":"CalibrationInterrupted","LocalizationID":"SE.AppDefinitions.PressMessages.Internal.Calibrations.CalibrationInterrupted","Data":{}}]},"CommitAvailability":{"IsAvailable":false,"UnavailableReasons":[{"ID":"CalibrationFailed","LocalizationID":"SE.AppDefinitions.PressMessages.Calibrations.CalibrationsGeneral.CalibrationFailed","Data":{}}]},"CommitState":"Idle","CancelAvailability":{"IsAvailable":false,"UnavailableReasons":[{"ID":"LPHNotReady","LocalizationID":"SE.AppDefinitions.PressMessages.LPH.LPHNotReady","Data":{"LPHID":{"Value":1,"Unit":"NoUnits"}}},{"ID":"LPHNotReady","LocalizationID":"SE.AppDefinitions.PressMessages.LPH.LPHNotReady","Data":{"LPHID":{"Value":2,"Unit":"NoUnits"}}},{"ID":"LPHNotReady","LocalizationID":"SE.AppDefinitions.PressMessages.LPH.LPHNotReady","Data":{"LPHID":{"Value":3,"Unit":"NoUnits"}}},{"ID":"LPHNotReady","LocalizationID":"SE.AppDefinitions.PressMessages.LPH.LPHNotReady","Data":{"LPHID":{"Value":4,"Unit":"NoUnits"}}},{"ID":"LPHNotReady","LocalizationID":"SE.AppDefinitions.PressMessages.LPH.LPHNotReady","Data":{"LPHID":{"Value":5,"Unit":"NoUnits"}}}]},"CancelState":"Idle","CalibrationId":"8ef3ab55-8738-4104-9372-f94ca0df8233","ScopeId":"af594a17-26ea-4ad5-8e74-fcbc575f6a6f","Errors":[],"StartAvailability":{"IsAvailable":false,"UnavailableReasons":[{"ID":"CprIlsRecalibrationNotAvailable","LocalizationID":"SE.AppDefinitions.PressMessages.Calibrations.CprIlsCalibration.CprIlsRecalibrationNotAvailable","Data":{}},{"ID":"PrintSessionInProgress","LocalizationID":"SE.AppDefinitions.PressMessages.PrintOperation.PrintSessionInProgress","Data":{}}]},"StopAvailability":{"IsAvailable":false,"UnavailableReasons":[{"ID":"OperationNotInProgress","LocalizationID":"SE.AppDefinitions.PressMessages.General.OperationNotInProgress","Data":{}}]},"State":"Failed","BuzzerableOperationState":"OperationCompleted","BuzzerState":"Needed","BuzzerType":"ForcedMethod1"},"NotificationType":"Changed"},"description":"BuzzerableCprIlsCalibrationFlowOperation/Changed"},{"name":"BuzzerableCprIlsCalibrationFlowOperation/Changed","id":"c1276b24-babf-4c62-b54e-f7f3190d7c58","data":{"resourceName":"BuzzerableCprIlsCalibrationFlowOperation","resourceContent":{"UseDefaultParameters":false,"LastCalibrationTime":"2023-09-17T14:58:15.4794191+03:00","CalibrationOperationDummy":false,"CalibrationState":"OperationCompleted","CalibrationResult":{"Status":"Failed","ResultMessages":[{"ID":"CalibrationInterrupted","LocalizationID":"SE.AppDefinitions.PressMessages.Internal.Calibrations.CalibrationInterrupted","Data":{}}]},"CommitAvailability":{"IsAvailable":false,"UnavailableReasons":[{"ID":"CalibrationFailed","LocalizationID":"SE.AppDefinitions.PressMessages.Calibrations.CalibrationsGeneral.CalibrationFailed","Data":{}}]},"CommitState":"Idle","CancelAvailability":{"IsAvailable":false,"UnavailableReasons":[{"ID":"LPHNotReady","LocalizationID":"SE.AppDefinitions.PressMessages.LPH.LPHNotReady","Data":{"LPHID":{"Value":2,"Unit":"NoUnits"}}},{"ID":"LPHNotReady","LocalizationID":"SE.AppDefinitions.PressMessages.LPH.LPHNotReady","Data":{"LPHID":{"Value":3,"Unit":"NoUnits"}}},{"ID":"LPHNotReady","LocalizationID":"SE.AppDefinitions.PressMessages.LPH.LPHNotReady","Data":{"LPHID":{"Value":4,"Unit":"NoUnits"}}},{"ID":"LPHNotReady","LocalizationID":"SE.AppDefinitions.PressMessages.LPH.LPHNotReady","Data":{"LPHID":{"Value":5,"Unit":"NoUnits"}}}]},"CancelState":"Idle","CalibrationId":"8ef3ab55-8738-4104-9372-f94ca0df8233","ScopeId":"af594a17-26ea-4ad5-8e74-fcbc575f6a6f","Errors":[],"StartAvailability":{"IsAvailable":false,"UnavailableReasons":[{"ID":"CprIlsRecalibrationNotAvailable","LocalizationID":"SE.AppDefinitions.PressMessages.Calibrations.CprIlsCalibration.CprIlsRecalibrationNotAvailable","Data":{}},{"ID":"PrintSessionInProgress","LocalizationID":"SE.AppDefinitions.PressMessages.PrintOperation.PrintSessionInProgress","Data":{}}]},"StopAvailability":{"IsAvailable":false,"UnavailableReasons":[{"ID":"OperationNotInProgress","LocalizationID":"SE.AppDefinitions.PressMessages.General.OperationNotInProgress","Data":{}}]},"State":"Failed","BuzzerableOperationState":"OperationCompleted","BuzzerState":"Needed","BuzzerType":"ForcedMethod1"},"NotificationType":"Changed"},"description":"BuzzerableCprIlsCalibrationFlowOperation/Changed"},{"name":"BuzzerableCprIlsCalibrationFlowOperation/Changed","id":"e605f0a4-7dc1-4cf7-baca-38565de28317","data":{"resourceName":"BuzzerableCprIlsCalibrationFlowOperation","resourceContent":{"UseDefaultParameters":false,"LastCalibrationTime":"2023-09-17T14:58:15.4794191+03:00","CalibrationOperationDummy":false,"CalibrationState":"OperationCompleted","CalibrationResult":{"Status":"Failed","ResultMessages":[{"ID":"CalibrationInterrupted","LocalizationID":"SE.AppDefinitions.PressMessages.Internal.Calibrations.CalibrationInterrupted","Data":{}}]},"CommitAvailability":{"IsAvailable":false,"UnavailableReasons":[{"ID":"CalibrationFailed","LocalizationID":"SE.AppDefinitions.PressMessages.Calibrations.CalibrationsGeneral.CalibrationFailed","Data":{}}]},"CommitState":"Idle","CancelAvailability":{"IsAvailable":false,"UnavailableReasons":[{"ID":"LPHNotReady","LocalizationID":"SE.AppDefinitions.PressMessages.LPH.LPHNotReady","Data":{"LPHID":{"Value":3,"Unit":"NoUnits"}}},{"ID":"LPHNotReady","LocalizationID":"SE.AppDefinitions.PressMessages.LPH.LPHNotReady","Data":{"LPHID":{"Value":4,"Unit":"NoUnits"}}},{"ID":"LPHNotReady","LocalizationID":"SE.AppDefinitions.PressMessages.LPH.LPHNotReady","Data":{"LPHID":{"Value":5,"Unit":"NoUnits"}}}]},"CancelState":"Idle","CalibrationId":"8ef3ab55-8738-4104-9372-f94ca0df8233","ScopeId":"af594a17-26ea-4ad5-8e74-fcbc575f6a6f","Errors":[],"StartAvailability":{"IsAvailable":false,"UnavailableReasons":[{"ID":"CprIlsRecalibrationNotAvailable","LocalizationID":"SE.AppDefinitions.PressMessages.Calibrations.CprIlsCalibration.CprIlsRecalibrationNotAvailable","Data":{}},{"ID":"PrintSessionInProgress","LocalizationID":"SE.AppDefinitions.PressMessages.PrintOperation.PrintSessionInProgress","Data":{}}]},"StopAvailability":{"IsAvailable":false,"UnavailableReasons":[{"ID":"OperationNotInProgress","LocalizationID":"SE.AppDefinitions.PressMessages.General.OperationNotInProgress","Data":{}}]},"State":"Failed","BuzzerableOperationState":"OperationCompleted","BuzzerState":"Needed","BuzzerType":"ForcedMethod1"},"NotificationType":"Changed"},"description":"BuzzerableCprIlsCalibrationFlowOperation/Changed"},{"name":"BuzzerableCprIlsCalibrationFlowOperation/Changed","id":"e876759f-5646-47e7-b39f-7baaec76d4fb","data":{"resourceName":"BuzzerableCprIlsCalibrationFlowOperation","resourceContent":{"UseDefaultParameters":false,"LastCalibrationTime":"2023-09-17T14:58:15.4794191+03:00","CalibrationOperationDummy":false,"CalibrationState":"OperationCompleted","CalibrationResult":{"Status":"Failed","ResultMessages":[{"ID":"CalibrationInterrupted","LocalizationID":"SE.AppDefinitions.PressMessages.Internal.Calibrations.CalibrationInterrupted","Data":{}}]},"CommitAvailability":{"IsAvailable":false,"UnavailableReasons":[{"ID":"CalibrationFailed","LocalizationID":"SE.AppDefinitions.PressMessages.Calibrations.CalibrationsGeneral.CalibrationFailed","Data":{}}]},"CommitState":"Idle","CancelAvailability":{"IsAvailable":false,"UnavailableReasons":[{"ID":"LPHNotReady","LocalizationID":"SE.AppDefinitions.PressMessages.LPH.LPHNotReady","Data":{"LPHID":{"Value":4,"Unit":"NoUnits"}}},{"ID":"LPHNotReady","LocalizationID":"SE.AppDefinitions.PressMessages.LPH.LPHNotReady","Data":{"LPHID":{"Value":5,"Unit":"NoUnits"}}}]},"CancelState":"Idle","CalibrationId":"8ef3ab55-8738-4104-9372-f94ca0df8233","ScopeId":"af594a17-26ea-4ad5-8e74-fcbc575f6a6f","Errors":[],"StartAvailability":{"IsAvailable":false,"UnavailableReasons":[{"ID":"CprIlsRecalibrationNotAvailable","LocalizationID":"SE.AppDefinitions.PressMessages.Calibrations.CprIlsCalibration.CprIlsRecalibrationNotAvailable","Data":{}},{"ID":"PrintSessionInProgress","LocalizationID":"SE.AppDefinitions.PressMessages.PrintOperation.PrintSessionInProgress","Data":{}}]},"StopAvailability":{"IsAvailable":false,"UnavailableReasons":[{"ID":"OperationNotInProgress","LocalizationID":"SE.AppDefinitions.PressMessages.General.OperationNotInProgress","Data":{}}]},"State":"Failed","BuzzerableOperationState":"OperationCompleted","BuzzerState":"Needed","BuzzerType":"ForcedMethod1"},"NotificationType":"Changed"},"description":"BuzzerableCprIlsCalibrationFlowOperation/Changed"},{"name":"BuzzerableCprIlsCalibrationFlowOperation/Changed","id":"f15c933b-4e2a-4e45-b6b4-515eb6bdac81","data":{"resourceName":"BuzzerableCprIlsCalibrationFlowOperation","resourceContent":{"UseDefaultParameters":false,"LastCalibrationTime":"2023-09-17T14:58:15.4794191+03:00","CalibrationOperationDummy":false,"CalibrationState":"OperationCompleted","CalibrationResult":{"Status":"Failed","ResultMessages":[{"ID":"CalibrationInterrupted","LocalizationID":"SE.AppDefinitions.PressMessages.Internal.Calibrations.CalibrationInterrupted","Data":{}}]},"CommitAvailability":{"IsAvailable":false,"UnavailableReasons":[{"ID":"CalibrationFailed","LocalizationID":"SE.AppDefinitions.PressMessages.Calibrations.CalibrationsGeneral.CalibrationFailed","Data":{}}]},"CommitState":"Idle","CancelAvailability":{"IsAvailable":false,"UnavailableReasons":[{"ID":"LPHNotReady","LocalizationID":"SE.AppDefinitions.PressMessages.LPH.LPHNotReady","Data":{"LPHID":{"Value":5,"Unit":"NoUnits"}}}]},"CancelState":"Idle","CalibrationId":"8ef3ab55-8738-4104-9372-f94ca0df8233","ScopeId":"af594a17-26ea-4ad5-8e74-fcbc575f6a6f","Errors":[],"StartAvailability":{"IsAvailable":false,"UnavailableReasons":[{"ID":"CprIlsRecalibrationNotAvailable","LocalizationID":"SE.AppDefinitions.PressMessages.Calibrations.CprIlsCalibration.CprIlsRecalibrationNotAvailable","Data":{}},{"ID":"PrintSessionInProgress","LocalizationID":"SE.AppDefinitions.PressMessages.PrintOperation.PrintSessionInProgress","Data":{}}]},"StopAvailability":{"IsAvailable":false,"UnavailableReasons":[{"ID":"OperationNotInProgress","LocalizationID":"SE.AppDefinitions.PressMessages.General.OperationNotInProgress","Data":{}}]},"State":"Failed","BuzzerableOperationState":"OperationCompleted","BuzzerState":"Needed","BuzzerType":"ForcedMethod1"},"NotificationType":"Changed"},"description":"BuzzerableCprIlsCalibrationFlowOperation/Changed"},{"name":"BuzzerableCprIlsCalibrationFlowOperation/Changed","id":"111906d3-579a-42a6-9f14-4e6205c35128","data":{"resourceName":"BuzzerableCprIlsCalibrationFlowOperation","resourceContent":{"UseDefaultParameters":false,"LastCalibrationTime":"2023-09-17T14:58:15.4794191+03:00","CalibrationOperationDummy":false,"CalibrationState":"OperationCompleted","CalibrationResult":{"Status":"Failed","ResultMessages":[{"ID":"CalibrationInterrupted","LocalizationID":"SE.AppDefinitions.PressMessages.Internal.Calibrations.CalibrationInterrupted","Data":{}}]},"CommitAvailability":{"IsAvailable":false,"UnavailableReasons":[{"ID":"CalibrationFailed","LocalizationID":"SE.AppDefinitions.PressMessages.Calibrations.CalibrationsGeneral.CalibrationFailed","Data":{}}]},"CommitState":"Idle","CancelAvailability":{"IsAvailable":true,"UnavailableReasons":[]},"CancelState":"Idle","CalibrationId":"8ef3ab55-8738-4104-9372-f94ca0df8233","ScopeId":"af594a17-26ea-4ad5-8e74-fcbc575f6a6f","Errors":[],"StartAvailability":{"IsAvailable":false,"UnavailableReasons":[{"ID":"CprIlsRecalibrationNotAvailable","LocalizationID":"SE.AppDefinitions.PressMessages.Calibrations.CprIlsCalibration.CprIlsRecalibrationNotAvailable","Data":{}},{"ID":"PrintSessionInProgress","LocalizationID":"SE.AppDefinitions.PressMessages.PrintOperation.PrintSessionInProgress","Data":{}}]},"StopAvailability":{"IsAvailable":false,"UnavailableReasons":[{"ID":"OperationNotInProgress","LocalizationID":"SE.AppDefinitions.PressMessages.General.OperationNotInProgress","Data":{}}]},"State":"Failed","BuzzerableOperationState":"OperationCompleted","BuzzerState":"Needed","BuzzerType":"ForcedMethod1"},"NotificationType":"Changed"},"description":"BuzzerableCprIlsCalibrationFlowOperation/Changed"},{"name":"BuzzerableCprIlsCalibrationFlowOperation/Changed","id":"c63e0144-7f97-42c2-86f5-a3e6253a4d5e","data":{"resourceName":"BuzzerableCprIlsCalibrationFlowOperation","resourceContent":{"UseDefaultParameters":false,"LastCalibrationTime":"2023-09-17T14:58:15.4794191+03:00","CalibrationOperationDummy":false,"CalibrationState":"OperationCompleted","CalibrationResult":{"Status":"Failed","ResultMessages":[{"ID":"CalibrationInterrupted","LocalizationID":"SE.AppDefinitions.PressMessages.Internal.Calibrations.CalibrationInterrupted","Data":{}}]},"CommitAvailability":{"IsAvailable":false,"UnavailableReasons":[{"ID":"CalibrationFailed","LocalizationID":"SE.AppDefinitions.PressMessages.Calibrations.CalibrationsGeneral.CalibrationFailed","Data":{}}]},"CommitState":"Idle","CancelAvailability":{"IsAvailable":true,"UnavailableReasons":[]},"CancelState":"Idle","CalibrationId":"8ef3ab55-8738-4104-9372-f94ca0df8233","ScopeId":"af594a17-26ea-4ad5-8e74-fcbc575f6a6f","Errors":[],"StartAvailability":{"IsAvailable":false,"UnavailableReasons":[{"ID":"CprIlsRecalibrationNotAvailable","LocalizationID":"SE.AppDefinitions.PressMessages.Calibrations.CprIlsCalibration.CprIlsRecalibrationNotAvailable","Data":{}},{"ID":"ScenarioConfigurationDisabled","LocalizationID":"ScenarioConfigurationDisabled","Data":{"MachineState":["READY"]}}]},"StopAvailability":{"IsAvailable":false,"UnavailableReasons":[{"ID":"OperationNotInProgress","LocalizationID":"SE.AppDefinitions.PressMessages.General.OperationNotInProgress","Data":{}}]},"State":"Failed","BuzzerableOperationState":"OperationCompleted","BuzzerState":"Needed","BuzzerType":"ForcedMethod1"},"NotificationType":"Changed"},"description":"BuzzerableCprIlsCalibrationFlowOperation/Changed"},{"name":"BuzzerableCprIlsCalibrationFlowOperation/Changed","id":"6ddc4e2f-a371-4d21-9c9b-6ee28c5edc26","data":{"resourceName":"BuzzerableCprIlsCalibrationFlowOperation","resourceContent":{"UseDefaultParameters":false,"LastCalibrationTime":"2023-09-17T14:58:15.4794191+03:00","CalibrationOperationDummy":false,"CalibrationState":"OperationCompleted","CalibrationResult":{"Status":"Failed","ResultMessages":[{"ID":"CalibrationInterrupted","LocalizationID":"SE.AppDefinitions.PressMessages.Internal.Calibrations.CalibrationInterrupted","Data":{}}]},"CommitAvailability":{"IsAvailable":false,"UnavailableReasons":[{"ID":"CalibrationFailed","LocalizationID":"SE.AppDefinitions.PressMessages.Calibrations.CalibrationsGeneral.CalibrationFailed","Data":{}}]},"CommitState":"Idle","CancelAvailability":{"IsAvailable":true,"UnavailableReasons":[]},"CancelState":"Idle","CalibrationId":"8ef3ab55-8738-4104-9372-f94ca0df8233","ScopeId":"af594a17-26ea-4ad5-8e74-fcbc575f6a6f","Errors":[],"StartAvailability":{"IsAvailable":false,"UnavailableReasons":[{"ID":"CprIlsRecalibrationNotAvailable","LocalizationID":"SE.AppDefinitions.PressMessages.Calibrations.CprIlsCalibration.CprIlsRecalibrationNotAvailable","Data":{}}]},"StopAvailability":{"IsAvailable":false,"UnavailableReasons":[{"ID":"OperationNotInProgress","LocalizationID":"SE.AppDefinitions.PressMessages.General.OperationNotInProgress","Data":{}}]},"State":"Failed","BuzzerableOperationState":"OperationCompleted","BuzzerState":"Needed","BuzzerType":"ForcedMethod1"},"NotificationType":"Changed"},"description":"BuzzerableCprIlsCalibrationFlowOperation/Changed"}],"id":"BuzzerableCprIlsCalibrationFlowOperation-start","name":"BuzzerableCprIlsCalibrationFlowOperation-start","description":"BuzzerableCprIlsCalibrationFlowOperation-start","parentTriggers":[],"dateModified":"1694953236185"}