{"repeat":false,"random":false,"durationBetweenWaves":"1200","waves":[{"name":"BuzzerableCprIlsCalibrationFlowOperation/Changed","id":"9b159c86-695f-44f1-960e-c114fcf3e87b","data":{"resourceName":"BuzzerableCprIlsCalibrationFlowOperation","resourceContent":{"UseDefaultParameters":false,"LastCalibrationTime":"2023-09-17T14:58:15.4794191+03:00","CalibrationOperationDummy":false,"CalibrationState":"NotStarted","CalibrationResult":{"Status":"None","ResultMessages":[]},"CommitAvailability":{"IsAvailable":false,"UnavailableReasons":[{"ID":"CalibrationNotStarted","LocalizationID":"SE.AppDefinitions.PressMessages.Calibrations.CalibrationsGeneral.CalibrationNotStarted","Data":{}}]},"CommitState":"Idle","CancelAvailability":{"IsAvailable":true,"UnavailableReasons":[]},"CancelState":"Idle","CalibrationId":"b0d980ad-92d5-479c-ae5e-c94e94c366a8","ScopeId":"af594a17-26ea-4ad5-8e74-fcbc575f6a6f","Errors":[],"StartAvailability":{"IsAvailable":false,"UnavailableReasons":[{"ID":"OperationStarting","LocalizationID":"SE.AppDefinitions.PressMessages.General.OperationStarting","Data":{}}]},"StopAvailability":{"IsAvailable":false,"UnavailableReasons":[{"ID":"OperationNotInProgress","LocalizationID":"SE.AppDefinitions.PressMessages.General.OperationNotInProgress","Data":{}}]},"State":"Idle","BuzzerableOperationState":"BuzzerLocking","BuzzerState":"NotNeeded","BuzzerType":"ForcedMethod1"},"NotificationType":"Changed"},"description":"BuzzerableCprIlsCalibrationFlowOperation/Changed"},{"name":"BuzzerableCprIlsCalibrationFlowOperation/Changed","id":"e0f0e503-246b-49f5-81c6-dcf6ed0c6721","data":{"resourceName":"BuzzerableCprIlsCalibrationFlowOperation","resourceContent":{"UseDefaultParameters":false,"LastCalibrationTime":"2023-09-17T14:58:15.4794191+03:00","CalibrationOperationDummy":false,"CalibrationState":"NotStarted","CalibrationResult":{"Status":"None","ResultMessages":[]},"CommitAvailability":{"IsAvailable":false,"UnavailableReasons":[{"ID":"CalibrationNotStarted","LocalizationID":"SE.AppDefinitions.PressMessages.Calibrations.CalibrationsGeneral.CalibrationNotStarted","Data":{}}]},"CommitState":"Idle","CancelAvailability":{"IsAvailable":true,"UnavailableReasons":[]},"CancelState":"Idle","CalibrationId":"b0d980ad-92d5-479c-ae5e-c94e94c366a8","ScopeId":"af594a17-26ea-4ad5-8e74-fcbc575f6a6f","Errors":[],"StartAvailability":{"IsAvailable":false,"UnavailableReasons":[{"ID":"OperationInProgress","LocalizationID":"SE.AppDefinitions.PressMessages.General.OperationInProgress","Data":{}}]},"StopAvailability":{"IsAvailable":false,"UnavailableReasons":[{"ID":"OperationStarting","LocalizationID":"SE.AppDefinitions.PressMessages.General.OperationStarting","Data":{}}]},"State":"InProgress","BuzzerableOperationState":"OperationInProgress","BuzzerState":"NotNeeded","BuzzerType":"ForcedMethod1"},"NotificationType":"Changed"},"description":"BuzzerableCprIlsCalibrationFlowOperation/Changed"},{"name":"BuzzerableCprIlsCalibrationFlowOperation/Changed","id":"1e823116-fd09-44eb-b996-6543b8b82a25","data":{"resourceName":"BuzzerableCprIlsCalibrationFlowOperation","resourceContent":{"UseDefaultParameters":false,"LastCalibrationTime":"2023-09-17T14:58:15.4794191+03:00","CalibrationOperationDummy":false,"CalibrationState":"OperationInProgress","CalibrationResult":{"Status":"None","ResultMessages":[]},"CommitAvailability":{"IsAvailable":false,"UnavailableReasons":[{"ID":"OperationInProgress","LocalizationID":"SE.AppDefinitions.PressMessages.General.OperationInProgress","Data":{}}]},"CommitState":"Idle","CancelAvailability":{"IsAvailable":false,"UnavailableReasons":[{"ID":"OperationInProgress","LocalizationID":"SE.AppDefinitions.PressMessages.General.OperationInProgress","Data":{}}]},"CancelState":"Idle","CalibrationId":"8ef3ab55-8738-4104-9372-f94ca0df8233","ScopeId":"af594a17-26ea-4ad5-8e74-fcbc575f6a6f","Errors":[],"StartAvailability":{"IsAvailable":false,"UnavailableReasons":[{"ID":"OperationInProgress","LocalizationID":"SE.AppDefinitions.PressMessages.General.OperationInProgress","Data":{}}]},"StopAvailability":{"IsAvailable":true,"UnavailableReasons":[]},"State":"InProgress","BuzzerableOperationState":"OperationInProgress","BuzzerState":"NotNeeded","BuzzerType":"ForcedMethod1"},"NotificationType":"Changed"},"description":"BuzzerableCprIlsCalibrationFlowOperation/Changed"},{"name":"BuzzerableCprIlsCalibrationFlowOperation/Changed","id":"fed1c8ee-ef64-48be-8346-2a307a63c911","data":{"resourceName":"BuzzerableCprIlsCalibrationFlowOperation","resourceContent":{"UseDefaultParameters":false,"LastCalibrationTime":"2023-09-17T14:58:15.4794191+03:00","CalibrationOperationDummy":false,"CalibrationState":"OperationInProgress","CalibrationResult":{"Status":"None","ResultMessages":[]},"CommitAvailability":{"IsAvailable":false,"UnavailableReasons":[{"ID":"OperationInProgress","LocalizationID":"SE.AppDefinitions.PressMessages.General.OperationInProgress","Data":{}}]},"CommitState":"Idle","CancelAvailability":{"IsAvailable":false,"UnavailableReasons":[{"ID":"OperationInProgress","LocalizationID":"SE.AppDefinitions.PressMessages.General.OperationInProgress","Data":{}}]},"CancelState":"Idle","CalibrationId":"8ef3ab55-8738-4104-9372-f94ca0df8233","ScopeId":"af594a17-26ea-4ad5-8e74-fcbc575f6a6f","Errors":[],"StartAvailability":{"IsAvailable":false,"UnavailableReasons":[{"ID":"OperationInProgress","LocalizationID":"SE.AppDefinitions.PressMessages.General.OperationInProgress","Data":{}}]},"StopAvailability":{"IsAvailable":true,"UnavailableReasons":[]},"State":"InProgress","BuzzerableOperationState":"OperationInProgress","BuzzerState":"Needed","BuzzerType":"ForcedMethod1"},"NotificationType":"Changed"},"description":"BuzzerableCprIlsCalibrationFlowOperation/Changed"},{"name":"BuzzerableCprIlsCalibrationFlowOperation/Changed","id":"a8b62432-7e41-4455-92e3-f8792b3689fe","data":{"resourceName":"BuzzerableCprIlsCalibrationFlowOperation","resourceContent":{"UseDefaultParameters":false,"LastCalibrationTime":"2023-09-17T14:58:15.4794191+03:00","CalibrationOperationDummy":false,"CalibrationState":"OperationCompletionInProgress","CalibrationResult":{"Status":"Succeeded","ResultMessages":[]},"CommitAvailability":{"IsAvailable":false,"UnavailableReasons":[{"ID":"OperationInProgress","LocalizationID":"SE.AppDefinitions.PressMessages.General.OperationInProgress","Data":{}}]},"CommitState":"Idle","CancelAvailability":{"IsAvailable":false,"UnavailableReasons":[{"ID":"OperationInProgress","LocalizationID":"SE.AppDefinitions.PressMessages.General.OperationInProgress","Data":{}}]},"CancelState":"Idle","CalibrationId":"8ef3ab55-8738-4104-9372-f94ca0df8233","ScopeId":"af594a17-26ea-4ad5-8e74-fcbc575f6a6f","Errors":[],"StartAvailability":{"IsAvailable":false,"UnavailableReasons":[{"ID":"OperationInProgress","LocalizationID":"SE.AppDefinitions.PressMessages.General.OperationInProgress","Data":{}}]},"StopAvailability":{"IsAvailable":false,"UnavailableReasons":[{"ID":"OperationNotInProgress","LocalizationID":"SE.AppDefinitions.PressMessages.General.OperationNotInProgress","Data":{}}]},"State":"InProgress","BuzzerableOperationState":"OperationInProgress","BuzzerState":"Needed","BuzzerType":"ForcedMethod1"},"NotificationType":"Changed"},"description":"BuzzerableCprIlsCalibrationFlowOperation/Changed"},{"name":"BuzzerableCprIlsCalibrationFlowOperation/Changed","id":"911b64b7-194a-4fde-8a51-9100c2e83ce3","data":{"resourceName":"BuzzerableCprIlsCalibrationFlowOperation","resourceContent":{"UseDefaultParameters":false,"LastCalibrationTime":"2023-09-17T14:58:15.4794191+03:00","CalibrationOperationDummy":false,"CalibrationState":"OperationCompletionInProgress","CalibrationResult":{"Status":"Succeeded","ResultMessages":[]},"CommitAvailability":{"IsAvailable":false,"UnavailableReasons":[{"ID":"OperationInProgress","LocalizationID":"SE.AppDefinitions.PressMessages.General.OperationInProgress","Data":{}}]},"CommitState":"Idle","CancelAvailability":{"IsAvailable":false,"UnavailableReasons":[{"ID":"OperationInProgress","LocalizationID":"SE.AppDefinitions.PressMessages.General.OperationInProgress","Data":{}}]},"CancelState":"Idle","CalibrationId":"8ef3ab55-8738-4104-9372-f94ca0df8233","ScopeId":"af594a17-26ea-4ad5-8e74-fcbc575f6a6f","Errors":[],"StartAvailability":{"IsAvailable":false,"UnavailableReasons":[{"ID":"OperationInProgress","LocalizationID":"SE.AppDefinitions.PressMessages.General.OperationInProgress","Data":{}}]},"StopAvailability":{"IsAvailable":false,"UnavailableReasons":[{"ID":"OperationNotInProgress","LocalizationID":"SE.AppDefinitions.PressMessages.General.OperationNotInProgress","Data":{}}]},"State":"InProgress","BuzzerableOperationState":"OperationInProgress","BuzzerState":"Needed","BuzzerType":"ForcedMethod1"},"NotificationType":"Changed"},"description":"BuzzerableCprIlsCalibrationFlowOperation/Changed"},{"name":"BuzzerableCprIlsCalibrationFlowOperation/Changed","id":"0cf337a9-57bf-43fa-be9a-2768b7dc925d","data":{"resourceName":"BuzzerableCprIlsCalibrationFlowOperation","resourceContent":{"UseDefaultParameters":false,"LastCalibrationTime":"2023-09-17T14:58:15.4794191+03:00","CalibrationOperationDummy":false,"CalibrationState":"OperationCompleted","CalibrationResult":{"Status":"Succeeded","ResultMessages":[]},"CommitAvailability":{"IsAvailable":true,"UnavailableReasons":[]},"CommitState":"Idle","CancelAvailability":{"IsAvailable":true,"UnavailableReasons":[]},"CancelState":"Idle","CalibrationId":"8ef3ab55-8738-4104-9372-f94ca0df8233","ScopeId":"af594a17-26ea-4ad5-8e74-fcbc575f6a6f","Errors":[],"StartAvailability":{"IsAvailable":true,"UnavailableReasons":[]},"StopAvailability":{"IsAvailable":false,"UnavailableReasons":[{"ID":"OperationNotInProgress","LocalizationID":"SE.AppDefinitions.PressMessages.General.OperationNotInProgress","Data":{}}]},"State":"Succeeded","BuzzerableOperationState":"OperationCompleted","BuzzerState":"Needed","BuzzerType":"ForcedMethod1"},"NotificationType":"Changed"},"description":"BuzzerableCprIlsCalibrationFlowOperation/Changed"}],"id":"cpr-calibration-start","name":"cpr-calibration-start","description":"cpr-calibration-start","parentTriggers":[],"dateModified":"1694954912249"}