{"repeat":false,"random":false,"durationBetweenWaves":100,"waves":[{"id":"e55f44a9-b88b-42f6-aa78-ec380d2daeeb","name":"LphServiceSequenceModeOperation/Changed","type":"socket","data":{"resourceName":"LphServiceSequenceModeOperation","NotificationType":"Changed","resourceContent":[{"IsReady":false,"CalibrationState":"OperationInProgress","CalibrationResult":{"Status":"None","ResultMessages":[]},"CommitAvailability":{"IsAvailable":false,"UnavailableReasons":[{"ID":"OperationInProgress","LocalizationID":"SE.AppDefinitions.PressMessages.General.OperationInProgress","Data":{}}]},"CommitState":"Idle","CancelAvailability":{"IsAvailable":false,"UnavailableReasons":[{"ID":"OperationInProgress","LocalizationID":"SE.AppDefinitions.PressMessages.General.OperationInProgress","Data":{}}]},"CancelState":"Idle","CalibrationId":"c614eadc-4066-4137-bb80-c834c8921348","ScopeId":"788b43a0-c04c-49b1-b6ae-4ce1f0b1ef6c","Errors":[],"StartAvailability":{"IsAvailable":false,"UnavailableReasons":[{"ID":"OperationInProgress","LocalizationID":"SE.AppDefinitions.PressMessages.General.OperationInProgress","Data":{}}]},"StopAvailability":{"IsAvailable":true,"UnavailableReasons":[]},"State":"InProgress","Stages":[{"Name":{"ID":"ServiceChained","LocalizationID":"SE.AppDefinitions.PressMessages.ChainedOperations.ServiceChained","Data":{}},"Status":"NotStarted"},{"Name":{"ID":"SequenceChained","LocalizationID":"SE.AppDefinitions.PressMessages.ChainedOperations.SequenceChained","Data":{}},"Status":"NotStarted"},{"Name":{"ID":"LphCoolingMechInitOperationChained","LocalizationID":"SE.AppDefinitions.PressMessages.ChainedOperations.LphCoolingMechInitOperationChained","Data":{}},"Status":"NotStarted"}],"Key":{"ID":"MEStation1"}}]}},{"id":"9ad264a5-1e81-4803-89e5-4faf0136e87d","name":"LphServiceSequenceModeOperation/Changed","type":"socket","data":{"resourceName":"LphServiceSequenceModeOperation","NotificationType":"Changed","resourceContent":[{"IsReady":false,"CalibrationState":"OperationInProgress","CalibrationResult":{"Status":"None","ResultMessages":[]},"CommitAvailability":{"IsAvailable":false,"UnavailableReasons":[{"ID":"OperationInProgress","LocalizationID":"SE.AppDefinitions.PressMessages.General.OperationInProgress","Data":{}}]},"CommitState":"Idle","CancelAvailability":{"IsAvailable":false,"UnavailableReasons":[{"ID":"OperationInProgress","LocalizationID":"SE.AppDefinitions.PressMessages.General.OperationInProgress","Data":{}}]},"CancelState":"Idle","CalibrationId":"c614eadc-4066-4137-bb80-c834c8921348","ScopeId":"788b43a0-c04c-49b1-b6ae-4ce1f0b1ef6c","Errors":[],"StartAvailability":{"IsAvailable":false,"UnavailableReasons":[{"ID":"OperationInProgress","LocalizationID":"SE.AppDefinitions.PressMessages.General.OperationInProgress","Data":{}}]},"StopAvailability":{"IsAvailable":true,"UnavailableReasons":[]},"State":"InProgress","Stages":[{"Name":{"ID":"ServiceChained","LocalizationID":"SE.AppDefinitions.PressMessages.ChainedOperations.ServiceChained","Data":{}},"Status":"Skipped"},{"Name":{"ID":"SequenceChained","LocalizationID":"SE.AppDefinitions.PressMessages.ChainedOperations.SequenceChained","Data":{}},"Status":"InProgress"},{"Name":{"ID":"LphCoolingMechInitOperationChained","LocalizationID":"SE.AppDefinitions.PressMessages.ChainedOperations.LphCoolingMechInitOperationChained","Data":{}},"Status":"NotStarted"}],"Key":{"ID":"MEStation1"}}]},"customWait":500},{"id":"5ee11eb4-fad6-4acc-981c-a5efcbe35b97","name":"LphReplacementInfoEntity/Initial","type":"socket","data":{"resourceName":"LphReplacementInfoEntity","NotificationType":"Changed","resourceContent":[{"LphReplacementInfo":{"LphPrintA3ImpCounterOnReplaced":0,"LphOnTimeCounterOnReplaced":0,"DetectedSerialNumber":"LPH1","DetectedSerialNumberUpdateTime":"2023-11-01T00:00:00+02:00"},"Timestamp":"2023-11-02T09:45:33.4346227+02:00","Key":{"ID":"MEStation1"}},{"Timestamp":"2023-10-31T14:14:14.1171233+02:00","Key":{"ID":"MEStation2"}},{"Timestamp":"2023-10-31T14:14:14.1172819+02:00","Key":{"ID":"MEStation3"}},{"Timestamp":"2023-10-31T14:14:14.1172874+02:00","Key":{"ID":"MEStation4"}},{"Timestamp":"2023-10-31T14:14:14.1172903+02:00","Key":{"ID":"MEStation5"}},{"Timestamp":"2023-10-31T14:14:14.117292+02:00","Key":{"ID":"MEStation6"}}]}},{"id":"70c61b3e-7734-4e20-a3a8-b518f9354990","name":"LphServiceSequenceModeOperation/Changed","type":"socket","data":{"resourceName":"LphServiceSequenceModeOperation","NotificationType":"Changed","resourceContent":[{"IsReady":false,"CalibrationState":"OperationCompleted","CalibrationResult":{"Status":"Succeeded","ResultMessages":[]},"CommitAvailability":{"IsAvailable":true,"UnavailableReasons":[]},"CommitState":"Idle","CancelAvailability":{"IsAvailable":true,"UnavailableReasons":[]},"CancelState":"Idle","CalibrationId":"c614eadc-4066-4137-bb80-c834c8921348","ScopeId":"788b43a0-c04c-49b1-b6ae-4ce1f0b1ef6c","Errors":[],"StartAvailability":{"IsAvailable":true,"UnavailableReasons":[]},"StopAvailability":{"IsAvailable":false,"UnavailableReasons":[{"ID":"OperationNotInProgress","LocalizationID":"SE.AppDefinitions.PressMessages.General.OperationNotInProgress","Data":{}}]},"State":"Succeeded","Stages":[{"Name":{"ID":"ServiceChained","LocalizationID":"SE.AppDefinitions.PressMessages.ChainedOperations.ServiceChained","Data":{}},"Status":"Skipped"},{"Name":{"ID":"SequenceChained","LocalizationID":"SE.AppDefinitions.PressMessages.ChainedOperations.SequenceChained","Data":{}},"Status":"Succeeded"},{"Name":{"ID":"LphCoolingMechInitOperationChained","LocalizationID":"SE.AppDefinitions.PressMessages.ChainedOperations.LphCoolingMechInitOperationChained","Data":{}},"Status":"Succeeded"}],"Key":{"ID":"MEStation1"}}]},"customWait":500},{"id":"daa4a038-dcc0-44cd-91a6-7ec9f9d79c48","name":"LphMechanicalResetOperation/Changed","type":"socket","data":{"resourceName":"LphMechanicalResetOperation","NotificationType":"Changed","resourceContent":[{"LogicalZones":["STATION_1_LPH_ENG_ZONE","STATION_2_LPH_ENG_ZONE","STATION_3_LPH_ENG_ZONE","STATION_4_LPH_ENG_ZONE","STATION_5_LPH_ENG_ZONE","STATION_6_LPH_ENG_ZONE","STATION_1_ASID_ZONE","STATION_2_ASID_ZONE","STATION_3_ASID_ZONE","STATION_4_ASID_ZONE","STATION_5_ASID_ZONE","STATION_6_ASID_ZONE"],"Errors":[],"StartAvailability":{"IsAvailable":true,"UnavailableReasons":[]},"StopAvailability":{"IsAvailable":false,"UnavailableReasons":[{"ID":"OperationNotInProgress","LocalizationID":"SE.AppDefinitions.PressMessages.General.OperationNotInProgress","Data":{}}]},"State":"Idle","Key":{"ID":"MEStation1"}}]},"customWait":0}],"id":"flow-80-1698910128314","name":"flow 80","description":"initial flow description","dateModified":"1698926032187"}