{"repeat":false,"random":false,"durationBetweenWaves":"50","waves":[{"name":"BuzzerableIlsSelfCalibrationFlowOperation/Changed","id":"aa2e5e38-4979-4922-962b-57437d59b8b6","data":{"resourceName":"BuzzerableIlsSelfCalibrationFlowOperation","resourceContent":{"CalibrationOperationDummy":false,"CalibrationState":"NotStarted","CalibrationResult":{"Status":"None","ResultMessages":[]},"CommitAvailability":{"IsAvailable":false,"UnavailableReasons":[{"ID":"CalibrationNotStarted","LocalizationID":"SE.AppDefinitions.PressMessages.Calibrations.CalibrationsGeneral.CalibrationNotStarted","Data":{}}]},"CommitState":"Idle","CancelAvailability":{"IsAvailable":true,"UnavailableReasons":[]},"CancelState":"Idle","CalibrationId":"28b26b9c-5fe9-4794-9141-f31ae568ff54","ScopeId":"d99081ab-5956-4ab8-99c8-01b0595d9716","Errors":[],"StartAvailability":{"IsAvailable":false,"UnavailableReasons":[{"ID":"BuzzerInProgress","LocalizationID":"SE.AppDefinitions.PressMessages.Buzzer.BuzzerInProgress","Data":{}}]},"StopAvailability":{"IsAvailable":false,"UnavailableReasons":[{"ID":"OperationNotInProgress","LocalizationID":"SE.AppDefinitions.PressMessages.General.OperationNotInProgress","Data":{}}]},"State":"Idle","Stages":[],"BuzzerableOperationState":"BuzzerBuzzing","BuzzerState":"Buzzing","BuzzerType":"ForcedMethod1"},"NotificationType":"Changed"}},{"name":"BuzzerableIlsSelfCalibrationFlowOperation/Changed","id":"aa2e5e38-4979-4922-962b-57437d59b8b5","data":{"resourceName":"BuzzerableIlsSelfCalibrationFlowOperation","resourceContent":{"CalibrationOperationDummy":false,"CalibrationState":"NotStarted","CalibrationResult":{"Status":"None","ResultMessages":[]},"CommitAvailability":{"IsAvailable":false,"UnavailableReasons":[{"ID":"CalibrationNotStarted","LocalizationID":"SE.AppDefinitions.PressMessages.Calibrations.CalibrationsGeneral.CalibrationNotStarted","Data":{}}]},"CommitState":"Idle","CancelAvailability":{"IsAvailable":true,"UnavailableReasons":[]},"CancelState":"Idle","CalibrationId":"28b26b9c-5fe9-4794-9141-f31ae568ff54","ScopeId":"d99081ab-5956-4ab8-99c8-01b0595d9716","Errors":[],"StartAvailability":{"IsAvailable":true,"UnavailableReasons":[]},"StopAvailability":{"IsAvailable":false,"UnavailableReasons":[{"ID":"OperationNotInProgress","LocalizationID":"SE.AppDefinitions.PressMessages.General.OperationNotInProgress","Data":{}}]},"State":"Idle","Stages":[],"BuzzerableOperationState":"Idle","BuzzerState":"NotNeeded","BuzzerType":"ForcedMethod1"},"NotificationType":"Changed"}},{"name":"BuzzerableIlsSelfCalibrationFlowOperation/Changed","id":"aa2e5e38-4979-4922-962b-57437d59b8b4","data":{"resourceName":"BuzzerableIlsSelfCalibrationFlowOperation","resourceContent":{"CalibrationOperationDummy":false,"CalibrationState":"NotStarted","CalibrationResult":{"Status":"None","ResultMessages":[]},"CommitAvailability":{"IsAvailable":false,"UnavailableReasons":[{"ID":"CalibrationNotStarted","LocalizationID":"SE.AppDefinitions.PressMessages.Calibrations.CalibrationsGeneral.CalibrationNotStarted","Data":{}}]},"CommitState":"Idle","CancelAvailability":{"IsAvailable":true,"UnavailableReasons":[]},"CancelState":"Idle","CalibrationId":"0e0796fe-888a-4f27-9bde-ab5ce9f23705","ScopeId":"d4ac9f04-3d21-4772-acdd-2a80f68d015c","Errors":[],"StartAvailability":{"IsAvailable":true,"UnavailableReasons":[]},"StopAvailability":{"IsAvailable":false,"UnavailableReasons":[{"ID":"OperationNotInProgress","LocalizationID":"SE.AppDefinitions.PressMessages.General.OperationNotInProgress","Data":{}}]},"State":"Idle","Stages":[],"BuzzerableOperationState":"Idle","BuzzerState":"NotNeeded","BuzzerType":"ForcedMethod1"},"NotificationType":"Changed"}},{"name":"BuzzerableIlsSelfCalibrationFlowOperation/Changed","id":"aa2e5e38-4979-4922-962b-57437d59b8b3","data":{"resourceName":"BuzzerableIlsSelfCalibrationFlowOperation","resourceContent":{"CalibrationOperationDummy":false,"CalibrationState":"NotStarted","CalibrationResult":{"Status":"None","ResultMessages":[]},"CommitAvailability":{"IsAvailable":false,"UnavailableReasons":[{"ID":"CalibrationNotStarted","LocalizationID":"SE.AppDefinitions.PressMessages.Calibrations.CalibrationsGeneral.CalibrationNotStarted","Data":{}}]},"CommitState":"Idle","CancelAvailability":{"IsAvailable":true,"UnavailableReasons":[]},"CancelState":"Idle","CalibrationId":"0e0796fe-888a-4f27-9bde-ab5ce9f23705","ScopeId":"d4ac9f04-3d21-4772-acdd-2a80f68d015c","Errors":[],"StartAvailability":{"IsAvailable":true,"UnavailableReasons":[]},"StopAvailability":{"IsAvailable":false,"UnavailableReasons":[{"ID":"OperationNotInProgress","LocalizationID":"SE.AppDefinitions.PressMessages.General.OperationNotInProgress","Data":{}}]},"State":"Idle","Stages":[],"BuzzerableOperationState":"Idle","BuzzerState":"Needed","BuzzerType":"ForcedMethod1"},"NotificationType":"Changed"}}],"id":"start-ils-calibration-buzzer","name":"start-ils-calibration-buzzer","description":"start-ils-calibration-buzzer","parentTriggers":[],"dateModified":"1692704778456"}