{
  "subcategories": [
    { "name": "Basic Operations", "id": "basicoperations", "categoryId": "operationalActions", "localizationId": "Menu.subcategories.basicoperations" },
    { "name": "Essential Utilities", "id": "essentialutilities", "categoryId": "operationalActions", "localizationId": "Menu.subcategories.essentialutilities" },
    { "name": "Substrate Operations", "id": "substrateoperations", "categoryId": "operationalActions", "localizationId": "Menu.subcategories.substrateoperations" },
    { "name": "Supply Replacement", "id": "supplyreplacement", "categoryId": "operationalActions", "localizationId": "Menu.subcategories.supplyreplacement" },
    { "name": "aSiD", "id": "asid", "categoryId": "calibrations", "localizationId": "Menu.subcategories.asid" },
    { "name": "BID", "id": "bid", "categoryId": "calibrations", "localizationId": "Menu.subcategories.bid" },
    { "name": "Blanket & Blanket Cleaning Roller (BCR)", "id": "blanketsticky", "categoryId": "calibrations", "localizationId": "Menu.subcategories.blanketsticky" },
    { "name": "Ink & Color", "id": "inkandcolor", "categoryId": "calibrations", "localizationId": "Menu.subcategories.inkandcolor" },
    { "name": "LED Printing Head (LPH)", "id": "lph", "categoryId": "calibrations", "localizationId": "Menu.subcategories.lph" },
    { "name": "Substrate", "id": "substrate", "categoryId": "calibrations", "localizationId": "Menu.subcategories.substrate" },
    { "name": "Other Calibrations", "id": "othercalibrations", "categoryId": "calibrations", "localizationId": "Menu.subcategories.othercalibrations" },
    { "name": "Diagnostics", "id": "diagnostics", "categoryId": "serviceAndTools", "localizationId": "Menu.subcategories.diagnostics" },
    { "name": "Tools", "id": "tools", "categoryId": "serviceAndTools", "localizationId": "Menu.subcategories.tools" },
    { "name": "Part Replacements", "id": "partreplacement", "categoryId": "serviceAndTools", "localizationId": "Menu.subcategories.partreplacement" },
    { "name": "Customer Support", "id": "customersupport", "categoryId": "serviceAndTools", "localizationId": "Menu.subcategories.customersupport" },
    { "name": "Press Status", "id": "pressstatus", "categoryId": "pressStatusAndSettings", "localizationId": "Menu.subcategories.pressstatus" },
    { "name": "Settings", "id": "settings", "categoryId": "pressStatusAndSettings", "localizationId": "Menu.subcategories.settings" }
  ],
  "tags": [
    { "name": "Color", "id": "color", "localizationId": "Menu.tags.color" },
    { "name": "None", "id": "none", "localizationId": "Menu.tags.none" }
  ],
  "processes": [
    {
      "isReadyForProduction": true,
      "name": "Color Calibration",
      "id": "ColorCalibrationWizard",
      "subcatagoryId": "inkandcolor",
      "tags": ["color"],
      "description": "Color Calibration",
      "subsystemId": "color",
      "localizationDescriptionId": "Menu.processes.ColorCalibrationWizard.description",
      "localizationId": "Menu.processes.ColorCalibrationWizard",
      "isExternal": false,
      "categoryId": "calibrations"
    },
    {
      "name": "Developer Tools",
      "id": "DevTools",
      "subcatagoryId": "settings",
      "tags": ["none"],
      "subsystemId": "calibration",
      "localizationId": "Menu.processes.DevTools",
      "description": "None",
      "localizationDescriptionId": "Menu.processes.DevTools.description",
      "categoryId": "pressStatusAndSettings"
    },
    {
      "name": "Automatic Alert Agent (AAA) settings",
      "isReadyForProduction": true,
      "id": "AAASettings",
      "subcatagoryId": "settings",
      "tags": ["none"],
      "description": "None",
      "subsystemId": "pws",
      "localizationDescriptionId": "Menu.processes.AAASettings.description",
      "localizationId": "Menu.processes.AAASettings",
      "isExternal": false,
      "categoryId": "pressStatusAndSettings"
    },
    {
      "name": "aSiD Replacement",
      "isReadyForProduction": true,
      "id": "AsidReplacementWizard",
      "subcatagoryId": "supplyreplacement",
      "tags": ["none"],
      "description": "None",
      "subsystemId": "printingEngine",
      "localizationDescriptionId": "Menu.processes.AsidReplacementWizard.description",
      "localizationId": "Menu.processes.AsidReplacementWizard",
      "isExternal": false,
      "categoryId": "operationalActions"
    },
    {
      "name": "aSiD Drive Speed Calibration",
      "isReadyForProduction": true,
      "id": "AsidSpeed",
      "subcatagoryId": "asid",
      "tags": ["none"],
      "description": "",
      "subsystemId": "calibration",
      "localizationId": "Menu.processes.AsidSpeed",
      "isExternal": false,
      "categoryId": "calibrations"
    },
    {
      "name": "Auto Bias Calibration",
      "isReadyForProduction": true,
      "id": "AutoBias",
      "subcatagoryId": "inkandcolor",
      "tags": ["none"],
      "description": "None",
      "subsystemId": "pws",
      "localizationDescriptionId": "Menu.processes.AutoBias.description",
      "localizationId": "Menu.processes.AutoBias",
      "isExternal": false,
      "categoryId": "calibrations"
    },
    {
      "name": "Backup and Restore Press Parameters",
      "isReadyForProduction": true,
      "id": "BackupAndRestore",
      "subcatagoryId": "tools",
      "tags": ["none"],
      "description": "None",
      "subsystemId": "ink",
      "localizationDescriptionId": "Menu.processes.BackupAndRestore.description",
      "localizationId": "Menu.processes.BackupAndRestore",
      "isExternal": false,
      "categoryId": "serviceAndTools"
    },
    {
      "name": "BID Engage Mechanical Calibration",
      "isReadyForProduction": true,
      "id": "BidEngageCalibration",
      "subcatagoryId": "bid",
      "tags": ["none"],
      "description": "BID Engage Mechanical Calibration",
      "subsystemId": "substrate",
      "localizationDescriptionId": "Menu.processes.BidEngageCalibration.description",
      "localizationId": "Menu.processes.BidEngageCalibration",
      "isExternal": false,
      "categoryId": "calibrations"
    },
    {
      "name": "BID Replacement",
      "isReadyForProduction": true,
      "id": "BidReplacement",
      "subcatagoryId": "supplyreplacement",
      "tags": ["none"],
      "subsystemId": "pws",
      "localizationId": "Menu.processes.BidReplacement",
      "isExternal": false,
      "categoryId": "operationalActions"
    },
    {
      "name": "Blanket Replacement",
      "isReadyForProduction": true,
      "id": "BlanketReplacement",
      "subcatagoryId": "supplyreplacement",
      "tags": ["none"],
      "description": "None",
      "subsystemId": "calibration",
      "localizationDescriptionId": "Menu.processes.BlanketReplacement.description",
      "localizationId": "Menu.processes.BlanketReplacement",
      "isExternal": false,
      "categoryId": "operationalActions"
    },
    {
      "name": "Blanket Conditioning",
      "isReadyForProduction": true,
      "id": "BlanketConditioning",
      "subcatagoryId": "basicoperations",
      "tags": ["none"],
      "description": "None",
      "subsystemId": "calibration",
      "localizationDescriptionId": "Menu.processes.BlanketConditioning.description",
      "localizationId": "Menu.processes.BlanketConditioning",
      "categoryId": "operationalActions"
    },
    {
      "name": "Blanket Cleaning",
      "isReadyForProduction": true,
      "id": "BlanketCleaning",
      "subcatagoryId": "basicoperations",
      "tags": ["none"],
      "description": "None",
      "subsystemId": "ink",
      "localizationDescriptionId": "Menu.processes.BlanketCleaning.description",
      "localizationId": "Menu.processes.BlanketCleaning",
      "isExternal": false,
      "categoryId": "operationalActions"
    },
    {
      "name": "Bypass Center",
      "isReadyForProduction": true,
      "id": "BypassCenter",
      "subcatagoryId": "diagnostics",
      "tags": ["none"],
      "description": "None",
      "subsystemId": "substrate",
      "localizationDescriptionId": "Menu.processes.BypassCenter.description",
      "localizationId": "Menu.processes.BypassCenter",
      "isExternal": false,
      "categoryId": "serviceAndTools"
    },
    {
      "name": "Color Change",
      "isReadyForProduction": true,
      "id": "ColorChangeWizard",
      "subcatagoryId": "tools",
      "tags": ["color"],
      "description": "None",
      "subsystemId": "color",
      "localizationDescriptionId": "Menu.processes.ColorChangeWizard.description",
      "localizationId": "Menu.processes.ColorChangeWizard",
      "isExternal": false,
      "categoryId": "serviceAndTools"
    },
    {
      "name": "Color Plane Registration (CPR) Calibration",
      "isReadyForProduction": true,
      "id": "CprCalibration",
      "subcatagoryId": "inkandcolor",
      "tags": ["none"],
      "description": "None",
      "subsystemId": "calibration",
      "localizationDescriptionId": "Menu.processes.CprCalibration.description",
      "localizationId": "Menu.processes.CprCalibration",
      "isExternal": false,
      "categoryId": "calibrations"
    },
    {
      "name": "Corner X Calibration",
      "isReadyForProduction": true,
      "isExternal": true,
      "id": "CornerX",
      "subcatagoryId": "lph",
      "tags": ["none"],
      "description": "None",
      "subsystemId": "substrate",
      "localizationDescriptionId": "Menu.processes.CornerX.description",
      "localizationId": "Menu.processes.CornerX",
      "categoryId": "calibrations"
    },
    {
      "name": "Doors and Covers",
      "isReadyForProduction": true,
      "id": "DoorsAndCovers",
      "subcatagoryId": "basicoperations",
      "tags": ["none"],
      "description": "None",
      "subsystemId": "pws",
      "localizationDescriptionId": "Menu.processes.DoorsAndCovers.description",
      "localizationId": "Menu.processes.DoorsAndCovers",
      "isExternal": false,
      "categoryId": "operationalActions"
    },
    {
      "name": "Dry BID",
      "id": "DryBid",
      "isReadyForProduction": true,
      "subcatagoryId": "basicoperations",
      "tags": ["none"],
      "description": "None",
      "subsystemId": "calibration",
      "localizationDescriptionId": "Menu.processes.DryBid.description",
      "localizationId": "Menu.processes.DryBid",
      "isExternal": false,
      "categoryId": "operationalActions"
    },
    {
      "name": "Element Activation Center",
      "id": "EACenter",
      "isReadyForProduction": true,
      "subcatagoryId": "diagnostics",
      "tags": ["none"],
      "description": "None",
      "subsystemId": "ink",
      "localizationDescriptionId": "Menu.processes.EACenter.description",
      "localizationId": "Menu.processes.EACenter",
      "isExternal": false,
      "categoryId": "serviceAndTools"
    },
    {
      "name": "In-Line Scanner (ILS) Calibration ",
      "id": "IlsCalibration",
      "isReadyForProduction": true,
      "subcatagoryId": "inkandcolor",
      "tags": ["none"],
      "description": "None",
      "subsystemId": "ink",
      "localizationDescriptionId": "Menu.processes.IlsCalibration.description",
      "localizationId": "Menu.processes.IlsCalibration",
      "isExternal": false,
      "categoryId": "calibrations"
    },
    {
      "name": "Ink Preparation",
      "id": "InkPreperation",
      "isReadyForProduction": true,
      "subcatagoryId": "basicoperations",
      "tags": ["none"],
      "description": "None",
      "subsystemId": "color",
      "localizationDescriptionId": "Menu.processes.InkPreperation.description",
      "localizationId": "Menu.processes.InkPreperation",
      "isExternal": false,
      "categoryId": "operationalActions"
    },
    {
      "name": "Ink Status",
      "id": "InkStatus",
      "isReadyForProduction": true,
      "subcatagoryId": "pressstatus",
      "tags": ["color"],
      "description": "None",
      "subsystemId": "color",
      "localizationDescriptionId": "Menu.processes.InkStatus.description",
      "localizationId": "Menu.processes.InkStatus",
      "isExternal": false,
      "categoryId": "pressStatusAndSettings"
    },
    {
      "name": "In-Line Primer (ILP) Wash",
      "id": "IlpWash",
      "isReadyForProduction": true,
      "subcatagoryId": "basicoperations",
      "tags": ["none"],
      "description": "None",
      "subsystemId": "pws",
      "localizationDescriptionId": "Menu.processes.IlpWash.description",
      "localizationId": "Menu.processes.IlpWash",
      "isExternal": false,
      "categoryId": "operationalActions"
    },
    {
      "name": "Ink Tank Flow Calibration",
      "id": "InkTankFlow",
      "isReadyForProduction": true,
      "subcatagoryId": "inkandcolor",
      "tags": ["none"],
      "description": "None",
      "subsystemId": "calibration",
      "localizationDescriptionId": "Menu.processes.InkTankFlow.description",
      "localizationId": "Menu.processes.InkTankFlow",
      "isExternal": false,
      "categoryId": "calibrations"
    },
    {
      "name": "Ink Tube Replacement",
      "id": "InkTubeReplacement",
      "isReadyForProduction": true,
      "subcatagoryId": "supplyreplacement",
      "tags": ["color"],
      "description": "None",
      "subsystemId": "ink",
      "localizationDescriptionId": "Menu.processes.InkTubeReplacement.description",
      "localizationId": "Menu.processes.InkTubeReplacement",
      "isExternal": false,
      "categoryId": "operationalActions"
    },
    {
      "name": "LED Printing Head (LPH) Focus Calibration",
      "id": "LPHFocus",
      "isReadyForProduction": true,
      "subcatagoryId": "lph",
      "tags": ["none"],
      "description": "None",
      "subsystemId": "calibration",
      "localizationDescriptionId": "Menu.processes.LPHFocus.description",
      "localizationId": "Menu.processes.LPHFocus",
      "isExternal": false,
      "categoryId": "calibrations"
    },
    {
      "name": "LED Printing Head (LPH) Uniformity Calibration",
      "id": "LphUniformity",
      "isReadyForProduction": true,
      "subcatagoryId": "lph",
      "tags": ["none"],
      "subsystemId": "substrate",
      "localizationId": "Menu.processes.LphUniformity",
      "isExternal": false,
      "categoryId": "calibrations"
    },
    {
      "name": "Other Calibrations",
      "id": "OtherCalibrations",
      "isReadyForProduction": true,
      "isExternal": true,
      "subcatagoryId": "othercalibrations",
      "tags": ["none"],
      "description": "None",
      "subsystemId": "substrate",
      "localizationDescriptionId": "Menu.processes.OtherCalibrations.description",
      "localizationId": "Menu.processes.OtherCalibrations",
      "categoryId": "calibrations"
    },
    {
      "name": "Printing Counters",
      "id": "PrintingCounters",
      "isReadyForProduction": true,
      "subcatagoryId": "pressstatus",
      "tags": ["none"],
      "description": "None",
      "subsystemId": "pws",
      "localizationDescriptionId": "Menu.processes.PrintingCounters.description",
      "localizationId": "Menu.processes.PrintingCounters",
      "isExternal": false,
      "categoryId": "pressStatusAndSettings"
    },
    {
      "name": "Substrate Scaling Correction",
      "id": "QuickScaling",
      "isReadyForProduction": true,
      "subcatagoryId": "substrate",
      "tags": ["none"],
      "description": "None",
      "subsystemId": "ink",
      "localizationDescriptionId": "Menu.processes.QuickScaling.description",
      "localizationId": "Menu.processes.QuickScaling",
      "isExternal": false,
      "categoryId": "calibrations"
    },
    {
      "name": "Blanket Cleaning Roller (BCR) Peeling",
      "id": "StirPeeling",
      "isReadyForProduction": true,
      "subcatagoryId": "basicoperations",
      "tags": ["none"],
      "description": "None",
      "subsystemId": "substrate",
      "localizationDescriptionId": "Menu.processes.StirPeeling.description",
      "localizationId": "Menu.processes.StirPeeling",
      "isExternal": false,
      "categoryId": "operationalActions"
    },
    {
      "name": "Substrate List",
      "id": "SubstrateList",
      "isReadyForProduction": true,
      "subcatagoryId": "essentialutilities",
      "tags": ["none"],
      "subsystemId": "substrate",
      "localizationId": "Menu.processes.SubstrateList",
      "isExternal": false,
      "categoryId": "operationalActions"
    },
    {
      "name": "Supplies Counters",
      "id": "SuppliesCounters",
      "isReadyForProduction": true,
      "subcatagoryId": "pressstatus",
      "tags": ["none"],
      "description": "None",
      "subsystemId": "pws",
      "localizationDescriptionId": "Menu.processes.SuppliesCounters.description",
      "localizationId": "Menu.processes.SuppliesCounters",
      "isExternal": false,
      "categoryId": "pressStatusAndSettings"
    },
    {
      "name": "Web Control",
      "id": "SystemWebFeed",
      "isReadyForProduction": true,
      "subcatagoryId": "substrateoperations",
      "tags": ["none"],
      "description": "None",
      "subsystemId": "substrate",
      "localizationDescriptionId": "Menu.processes.SystemWebFeed.description",
      "localizationId": "Menu.processes.SystemWebFeed",
      "isExternal": false,
      "categoryId": "operationalActions"
    },
    {
      "name": "Blanket Cleaning Roller (BCR) Engage Force Calibration",
      "id": "StickyRoller",
      "isReadyForProduction": true,
      "subcatagoryId": "blanketsticky",
      "tags": ["none"],
      "description": "None",
      "subsystemId": "pws",
      "localizationDescriptionId": "Menu.processes.StickyRoller.description",
      "localizationId": "Menu.processes.StickyRoller",
      "isExternal": false,
      "categoryId": "calibrations"
    },
    {
      "name": "Monitor Setup",
      "id": "ScreenSetup",
      "isReadyForProduction": true,
      "subcatagoryId": "settings",
      "tags": ["none"],
      "description": "None",
      "subsystemId": "substrate",
      "localizationDescriptionId": "Menu.processes.ScreenSetup.description",
      "localizationId": "Menu.processes.ScreenSetup",
      "isExternal": false,
      "categoryId": "pressStatusAndSettings"
    },
    {
      "name": "Unwinder Roll Replacement",
      "id": "UnwinderRollReplacement",
      "isReadyForProduction": true,
      "subcatagoryId": "substrateoperations",
      "tags": ["none"],
      "subsystemId": "substrate",
      "localizationId": "Menu.processes.UnwinderRollReplacement",
      "isExternal": false,
      "categoryId": "operationalActions"
    },
    {
      "name": "PWS Web Guide",
      "id": "WebGuide",
      "subcatagoryId": "substrateoperations",
      "tags": ["none"],
      "subsystemId": "pws",
      "localizationId": "Menu.processes.WebGuide",
      "isReadyForProduction": true,
      "isExternal": false,
      "categoryId": "operationalActions"
    },
    {
      "name": "Web Handling System (WHS) Relative Speed Calibration ",
      "id": "WHSRelativeSpeedCalibration",
      "isReadyForProduction": true,
      "subcatagoryId": "substrate",
      "tags": ["none"],
      "description": "",
      "subsystemId": "calibration",
      "localizationDescriptionId": "Menu.processes.WHSRelativeSpeedCalibration.description",
      "localizationId": "Menu.processes.WHSRelativeSpeedCalibration",
      "isExternal": false,
      "categoryId": "calibrations"
    },
    {
      "name": "Press Configuration",
      "id": "PressConfiguration",
      "subcatagoryId": "service",
      "tags": ["none"],
      "description": "",
      "subsystemId": "substrate",
      "localizationDescriptionId": "Menu.processes.PressConfiguration.description",
      "localizationId": "Menu.processes.PressConfiguration",
      "categoryId": "calibrations"
    },
    {
      "name": "Installation Center",
      "id": "InstallationCenter",
      "subcatagoryId": "tools",
      "tags": ["none"],
      "subsystemId": "printingEngine",
      "localizationId": "Menu.processes.InstallationCenter",
      "isReadyForProduction": false,
      "isExternal": false,
      "categoryId": "serviceAndTools"
    },
    {
      "name": "Service Call",
      "id": "ServiceCall",
      "isExternal": true,
      "subcatagoryId": "customersupport",
      "tags": ["none"],
      "description": "",
      "subsystemId": "ink",
      "localizationDescriptionId": "Menu.processes.ServiceCall.description",
      "localizationId": "Menu.processes.ServiceCall",
      "isReadyForProduction": true,
      "categoryId": "serviceAndTools"
    },
    {
      "name": "Safety Device Updates",
      "id": "SlcAutoDownload",
      "subcatagoryId": "tools",
      "tags": ["none"],
      "subsystemId": "printingEngine",
      "localizationId": "Menu.processes.SlcAutoDownload",
      "isReadyForProduction": false,
      "isExternal": false,
      "categoryId": "serviceAndTools"
    },
    {
      "name": "Rewinder Roll Replacement",
      "isReadyForProduction": true,
      "id": "RewinderRollReplacement",
      "subcatagoryId": "substrateoperations",
      "tags": ["none"],
      "subsystemId": "substrate",
      "localizationId": "Menu.processes.RewinderRollReplacement",
      "isExternal": false,
      "categoryId": "operationalActions"
    },
    {
      "name": "Message Center",
      "id": "MessageCenter",
      "subcatagoryId": "essentialutilities",
      "tags": ["none"],
      "description": "None",
      "subsystemId": "calibration",
      "isReadyForProduction": true,
      "isExternal": false,
      "localizationDescriptionId": "Menu.processes.MessageCenter.description",
      "localizationId": "Menu.processes.MessageCenter",
      "categoryId": "operationalActions"
    },
    {
      "name": "Tensioner Calibration",
      "id": "TensionerMechanicalCalibration",
      "subcatagoryId": "blanketsticky",
      "tags": ["none"],
      "subsystemId": "calibration",
      "isReadyForProduction": true,
      "isExternal": false,
      "localizationId": "Menu.processes.TensionerMechanicalCalibration",
      "categoryId": "calibrations"
    },
    {
      "name": "Ink Level Sensor Calibration",
      "id": "InkTankLevelPressureSensorCalibration",
      "subcatagoryId": "basicoperations",
      "tags": ["none"],
      "subsystemId": "calibration",
      "isReadyForProduction": false,
      "isExternal": false,
      "localizationDescriptionId": "Menu.processes.InkTankLevelPressureSensorCalibration.description",
      "localizationId": "Menu.processes.InkTankLevelPressureSensorCalibration",
      "categoryId": "calibrations"
    },
    {
      "name": "Ink SAS - RDU Pressure sensor calibration",
      "id": "InkSasPressureSensorCalibration",
      "subcatagoryId": "othercalibrations",
      "tags": ["none"],
      "subsystemId": "ink",
      "isReadyForProduction": false,
      "isExternal": false,
      "localizationDescriptionId": "Menu.processes.InkSasPressureSensorCalibration.description",
      "localizationId": "Menu.processes.InkSasPressureSensorCalibration",
      "categoryId": "calibrations"
    },
    {
      "name": "ImO Buffer (CS Return) sensor calibration",
      "id": "ImoCSReturnSensorCalibration",
      "subcatagoryId": "basicoperations",
      "tags": ["none"],
      "subsystemId": "calibration",
      "isReadyForProduction": false,
      "isExternal": false,
      "localizationDescriptionId": "Menu.processes.ImoCSReturnSensorCalibration.description",
      "localizationId": "Menu.processes.ImoCSReturnSensorCalibration",
      "categoryId": "calibrations"
    },
    {
      "name": "ImO Reservoir sensor calibration",
      "id": "ImoReservoirSensorCalibration",
      "subcatagoryId": "basicoperations",
      "tags": ["none"],
      "subsystemId": "calibration",
      "isReadyForProduction": false,
      "isExternal": false,
      "localizationDescriptionId": "Menu.processes.ImoReservoirSensorCalibration.description",
      "localizationId": "Menu.processes.ImoReservoirSensorCalibration",
      "categoryId": "calibrations"
    }
  ],
  "initialProcesses": {
    "operationalActions": [
      "BlanketReplacement",
      "UnwinderRollReplacement",
      "RewinderRollReplacement",
      "InkPreperation",
      "InkTubeReplacement",
      "AsidReplacementWizard",
      "BidReplacement",
      "DoorsAndCovers"
    ],
    "calibrations": [
      "AsidSpeed",
      "BidEngageCalibration",
      "IlsCalibration",
      "LPHFocus",
      "InkTankFlow",
      "InkTankLevelPressureSensorCalibration",
      "WHSRelativeSpeedCalibration",
      "ImoReservoirSensorCalibration",
      "InkSasPressureSensorCalibration",
      "ImoCSReturnSensorCalibration"
    ],
    "serviceAndTools": ["EACenter", "BypassCenter", "ColorChangeWizard", "SlcAutoDownload", "InstallationCenter", "ServiceCall"],
    "cleaningProcedures": [],
    "pressStatusAndSettings": ["SuppliesCounters", "InkStatus", "AAASettings", "PrintingCounters", "ScreenSetup"]
  },
  "categories": [
    {
      "id": "operationalActions",
      "name": "Operational Actions",
      "description": "Supply replacements, basic operations, and essential production actions",
      "localizationDescriptionId": "Menu.categories.operationalActions.description",
      "localizationId": "Menu.categories.operationalActions"
    },
    {
      "id": "calibrations",
      "name": "Calibrations",
      "description": "Press cleaning procedures and basic maintenance routines",
      "localizationDescriptionId": "Menu.categories.calibrations.description",
      "localizationId": "Menu.categories.calibrations"
    },
    {
      "id": "serviceAndTools",
      "name": "Service and Tools",
      "description": "Diagnostics, press tools, part replacements and customer support",
      "localizationDescriptionId": "Menu.categories.serviceAndTools.description",
      "localizationId": "Menu.categories.serviceAndTools"
    },
    {
      "id": "cleaningProcedures",
      "name": "Cleaning Procedures",
      "description": "Press cleaning procedures and basic maintenance routines",
      "localizationDescriptionId": "Menu.categories.cleaningProcedures.description",
      "localizationId": "Menu.categories.cleaningProcedures"
    },
    {
      "id": "pressStatusAndSettings",
      "name": "Press Status and Settings",
      "description": "Press and subsystem settings, Information and status",
      "localizationDescriptionId": "Menu.categories.pressStatusAndSettings.description",
      "localizationId": "Menu.categories.pressStatusAndSettings"
    }
  ]
}
